{
    "type":"unique-value",
    "field":"AGE_HS",
    "field2":null,
    "field3":null,
    "fieldDelimiter":", ",
    "uniqueValueInfos":[
        {
            "symbol":{
                "type":"simple-marker",
                "style":"circle",
                "color":[
                    69,
                    117,
                    181,
                    255
                ],
                "size":6,
                "angle":0,
                "xoffset":0,
                "yoffset":0,
                "outline":{
                    "color":[0,0,0,255],
                    "width":1
                }
            },
            "value":"-3",
            "label":"Cold Spot - 99% Confidence (young)",
            "description":null
        },
        {
            "symbol":{
                "type":"simple-marker",
                "style":"circle",
                "color":[
                    132,
                    158,
                    186,
                    255
                ],
                "size":6,
                "angle":0,
                "xoffset":0,
                "yoffset":0,
                "outline":{
                    "color":[0,0,0,255],
                    "width":1
                }
            },
            "value":"-2",
            "label":"Cold Spot - 95% Confidence (young)",
            "description":null
        },
        {
            "symbol":{
                "type":"simple-marker",
                "style":"circle",
                "color":[
                    192,
                    204,
                    190,
                    255
                ],
                "size":6,
                "angle":0,
                "xoffset":0,
                "yoffset":0,
                "outline":{
                    "color":[0,0,0,255],
                    "width":1
                }
            },
            "value":"-1",
            "label":"Cold Spot - 90% Confidence (young)",
            "description":null
        },
        {
            "symbol":{
                "type":"simple-marker",
                "style":"circle",
                "color":[
                    255,
                    255,
                    191,
                    255
                ],
                "size":6,
                "angle":0,
                "xoffset":0,
                "yoffset":0,
                "outline":{
                    "color":[0,0,0,255],
                    "width":1
                }
            },
            "value":"0",
            "label":"Not Significant",
            "description":null
        },
        {
            "symbol":{
                "type":"simple-marker",
                "style":"circle",
                "color":[
                    250,
                    185,
                    132,
                    255
                ],
                "size":6,
                "angle":0,
                "xoffset":0,
                "yoffset":0,
                "outline":{
                    "color":[0,0,0,255],
                    "width":1
                }
            },
            "value":"1",
            "label":"Hot Spot - 90% Confidence (old)",
            "description":null
        },
        {
            "symbol":{
                "type":"simple-marker",
                "style":"circle",
                "color":[
                    237,
                    117,
                    81,
                    255
                ],
                "size":6,
                "angle":0,
                "xoffset":0,
                "yoffset":0,
                "outline":{
                    "color":[0,0,0,255],
                    "width":1
                }
            },
            "value":"2",
            "label":"Hot Spot - 95% Confidence (old)",
            "description":null
        },
        {
            "symbol":{
                "type":"simple-marker",
                "style":"circle",
                "color":[
                    214,
                    47,
                    39,
                    255
                ],
                "size":6,
                "angle":0,
                "xoffset":0,
                "yoffset":0,
                "outline":{
                    "color":[0,0,0,255],
                    "width":1
                }
            },
            "value":"3",
            "label":"Hot Spot - 99% Confidence (old)",
            "description":null
        }
    ]
}